econvert/__init__.py
econvert/econvert.py
econvert-0.0.1.data/scripts/econvert.py
econvert-0.0.1.dist-info/LICENSE.txt
econvert-0.0.1.dist-info/METADATA
econvert-0.0.1.dist-info/WHEEL
econvert-0.0.1.dist-info/top_level.txt
econvert-0.0.1.dist-info/RECORD
