Metadata-Version: 2.1
Name: econvert
Version: 0.0.1
Summary: Hassle-free convertions
Home-page: https://github.com/YFOMNN/econvert
Author: Mohammmed Yaseen
Author-email: hmyaseen05@gmail.com
License: MIT
Platform: UNKNOWN
Classifier: License :: OSI Approved :: MIT License
Classifier: Programming Language :: Python :: 3
